{
  "required": true,
  "minVersion": "0.8",
  "package": "mekanismaddupgradeslots.mixins",
  "refmap": "mixins.mekanismaddupgradeslots.refmap.json",
  "compatibilityLevel": "JAVA_8",
  "mixins": [
    "generator.wind.MixinTileEntityWindGenerator",
    "generator.wind.MixinGuiWindGenerator",
    "generator.heat.MixinTileEntityHeatGenerator",
    "generator.heat.MixinGuiHeatGenerator",
    "generator.bio.MixinTileEntityBioGenerator",
    "generator.bio.MixinGuiBioGenerator",
    "generator.gas.MixinTileEntityGasGenerator",
    "generator.gas.MixinGuiGasGenerator",
    "generator.solar.MixinTileEntitySolarGenerator",
    "generator.solar.MixinGuiSolarGenerator",
    "laser.amplifier.MixinTileEntityLaserAmplifier",
    "laser.amplifier.MixinGuiLaserAmplifier",
    "laser.tractorbeam.MixinTileEntityLaserTractorBeam",
    "laser.tractorbeam.MixinGuiLaserTractorBeam"


  ],
  "client": [],
  "server": []
}
